{
    "parent": "c_mnmz:rock/calcite",
    "criteria": {
        "0": {
            "trigger": "minecraft:inventory_changed"
        }
    },
    "display": {
        "title": [
            {"translate": "mnmz.how_to_get","fallback": "How to get "},
            {"translate": "block.minecraft.tuff"}
        ],
        "description": [
            {
                "color": "#F58220",
                "translate": "create.recipe.packing"
            },
            {"text": ":\n"},
            {
                "translate": "item.minecraft.iron_nugget"
            },
            {"text": "*1\n"},
            {
                "translate": "item.minecraft.gold_nugget"
            },
            {"text": "*1\n"},
            {
                "translate": "item.create.copper_nugget"
            },
            {"text": "*1\n"},
            {
                "translate": "item.create.zinc_nugget"
            },
            {"text": "*1\n"},
            {
                "translate": "item.minecraft.flint"
            },
            {"text": "*5\n"},
            {
                "translate": "block.minecraft.lava"
            },
            {"text": "*400mB\n↑\n"},
            {
                "translate": "create.recipe.heat_requirement.superheated"
            }
        ],
        "icon": {
            "count": 1,
            "id": "minecraft:tuff"
        },
        "show_toast": false,
        "announce_to_chat": false
    },
    "requirements": [
        [
            "0"
        ]
    ],
    "sends_telemetry_event": false
}